[
  {
    "name": "Hacker News",
    "url": "https://news.ycombinator.com",
    "feed": "https://news.ycombinator.com/rss",
    "category": "news"
  },
  {
    "name": "Lobsters",
    "url": "https://lobste.rs",
    "feed": "https://lobste.rs/rss",
    "category": "news"
  },
  {
    "name": "The Register",
    "url": "https://www.theregister.com",
    "feed": "https://www.theregister.com/headlines.atom",
    "category": "news"
  },
  {
    "name": "Ars Technica",
    "url": "https://arstechnica.com",
    "feed": "https://feeds.arstechnica.com/arstechnica/index",
    "category": "news"
  },
  {
    "name": "TechCrunch",
    "url": "https://techcrunch.com",
    "feed": "https://techcrunch.com/feed/",
    "category": "news"
  },
  {
    "name": "The Verge",
    "url": "https://www.theverge.com",
    "feed": "https://www.theverge.com/rss/tech/index.xml",
    "category": "news"
  },
  {
    "name": "Publickey",
    "url": "https://www.publickey1.jp",
    "feed": "https://www.publickey1.jp/atom.xml",
    "category": "news"
  },
  {
    "name": "Gihyo (技術評論社)",
    "url": "https://gihyo.jp",
    "feed": "https://gihyo.jp/feed/atom",
    "category": "news"
  },
  {
    "name": "はてなブックマーク IT",
    "url": "https://b.hatena.ne.jp/hotentry/it",
    "feed": "https://b.hatena.ne.jp/hotentry/it.rss",
    "category": "news"
  },
  {
    "name": "dev.to",
    "url": "https://dev.to",
    "feed": "https://dev.to/feed",
    "category": "blog"
  },
  {
    "name": "Zenn",
    "url": "https://zenn.dev",
    "feed": "https://zenn.dev/feed",
    "category": "blog"
  },
  {
    "name": "InfoQ",
    "url": "https://www.infoq.com",
    "feed": "https://www.infoq.com/feed/",
    "category": "blog"
  },
  {
    "name": "Hugging Face Blog",
    "url": "https://huggingface.co/blog",
    "feed": "https://huggingface.co/blog/feed.xml",
    "category": "blog"
  },
  {
    "name": "Simon Willison's Weblog",
    "url": "https://simonwillison.net",
    "feed": "https://simonwillison.net/atom/everything/",
    "category": "blog"
  },
  {
    "name": "Martin Fowler",
    "url": "https://martinfowler.com",
    "feed": "https://martinfowler.com/feed.atom",
    "category": "blog"
  },
  {
    "name": "Smashing Magazine",
    "url": "https://www.smashingmagazine.com",
    "feed": "https://www.smashingmagazine.com/feed/",
    "category": "blog"
  },
  {
    "name": "DevelopersIO",
    "url": "https://dev.classmethod.jp",
    "feed": "https://dev.classmethod.jp/feed/",
    "category": "blog"
  },
  {
    "name": "Cloudflare Blog",
    "url": "https://blog.cloudflare.com",
    "feed": "https://blog.cloudflare.com/rss/",
    "category": "enterprise"
  },
  {
    "name": "GitHub Blog",
    "url": "https://github.blog",
    "feed": "https://github.blog/feed/",
    "category": "enterprise"
  },
  {
    "name": "Google Research Blog",
    "url": "https://research.google/blog/",
    "feed": "https://research.google/blog/rss/",
    "category": "enterprise"
  },
  {
    "name": "Microsoft Engineering",
    "url": "https://devblogs.microsoft.com/engineering-at-microsoft/",
    "feed": "https://devblogs.microsoft.com/engineering-at-microsoft/feed/",
    "category": "enterprise"
  },
  {
    "name": "GitLab Blog",
    "url": "https://about.gitlab.com/blog/",
    "feed": "https://about.gitlab.com/atom.xml",
    "category": "enterprise"
  },
  {
    "name": "Spotify Engineering",
    "url": "https://engineering.atspotify.com",
    "feed": "https://engineering.atspotify.com/feed",
    "category": "enterprise"
  },
  {
    "name": "Meta Engineering",
    "url": "https://engineering.fb.com",
    "feed": "https://engineering.fb.com/feed/",
    "category": "enterprise"
  },
  {
    "name": "AWS News Blog",
    "url": "https://aws.amazon.com/blogs/aws",
    "feed": "https://aws.amazon.com/blogs/aws/feed/",
    "category": "enterprise"
  },
  {
    "name": "LY Corp Tech Blog",
    "url": "https://techblog.lycorp.co.jp/ja",
    "feed": "https://techblog.lycorp.co.jp/ja/feed/index.xml",
    "category": "enterprise"
  },
  {
    "name": "CNCF Blog",
    "url": "https://www.cncf.io/blog",
    "feed": "https://www.cncf.io/feed/",
    "category": "oss"
  },
  {
    "name": "Kubernetes Blog",
    "url": "https://kubernetes.io/blog/",
    "feed": "https://kubernetes.io/feed.xml",
    "category": "oss"
  },
  {
    "name": "Rust Language Blog",
    "url": "https://blog.rust-lang.org",
    "feed": "https://blog.rust-lang.org/feed.xml",
    "category": "oss"
  },
  {
    "name": "opensource.com",
    "url": "https://opensource.com",
    "feed": "https://opensource.com/feed",
    "category": "oss"
  }
]
